hj-dezero/__init__.py
hj-dezero/core.py
hj-dezero/core_simple.py
hj-dezero/cuda.py
hj-dezero/dataloaders.py
hj-dezero/datasets.py
hj-dezero/functions.py
hj-dezero/functions_conv.py
hj-dezero/layers.py
hj-dezero/models.py
hj-dezero/optimizers.py
hj-dezero/transforms.py
hj-dezero/utils.py
hj_dezero/__init__.py
hj_dezero/core.py
hj_dezero/core_simple.py
hj_dezero/cuda.py
hj_dezero/dataloaders.py
hj_dezero/datasets.py
hj_dezero/functions.py
hj_dezero/functions_conv.py
hj_dezero/layers.py
hj_dezero/models.py
hj_dezero/optimizers.py
hj_dezero/transforms.py
hj_dezero/utils.py
hj_dezero-0.0.0.dist-info/METADATA
hj_dezero-0.0.0.dist-info/WHEEL
hj_dezero-0.0.0.dist-info/top_level.txt
hj_dezero-0.0.0.dist-info/RECORD
